LICENSE
README.md
setup.py
base/__init__.py
base/commonera.py
base/consts.py
base/controllers.py
base/enums.py
base/errors.py
base/filetypes.py
base/regexp.py
base/registry.py
base/testing.py
base/things.py
base/whens.py
base/rightdown/__init__.py
base/rightdown/blocks.py
base/rightdown/commandline.py
base/rightdown/enums.py
base/rightdown/errors.py
base/rightdown/parser.py
base/rightdown/patterns.py
base/rightdown/printers.py
base/rightdown/rightdown.py
base/rightdown/tests.py
base/rightdown/textblock.py
base/rightdown/tokens.py
base/utils/__init__.py
base/utils/decorators.py
base/utils/django.py
base/utils/environment.py
base/utils/fuzzy.py
base/utils/interactive.py
base/utils/iterables.py
base/utils/logging.py
base/utils/metaclasses.py
base/utils/misc.py
base/utils/strings.py
base/utils/tests.py
base/utils/threadstacks.py
base/utils/time.py
octobase.egg-info/PKG-INFO
octobase.egg-info/SOURCES.txt
octobase.egg-info/dependency_links.txt
octobase.egg-info/top_level.txt