Metadata-Version: 2.1
Name: octobase
Version: 0.9.6
Summary: The First Building Block For Any Python Project
Home-page: https://bitbucket.org/octoboxy/octobase/
Author: Octoboxy
Author-email: office@octoboxy.com
Classifier: Programming Language :: Python :: 3
Classifier: License :: OSI Approved :: Apache Software License
Classifier: Operating System :: OS Independent
Classifier: Development Status :: 4 - Beta
Requires-Python: >=3.9
License-File: LICENSE
